Metadata-Version: 2.1
Name: StockTrackr
Version: 0.2.4
Summary: A basic stock data puller/monitor
Home-page: https://github.com/jwalshdev/StockTrackr
Author: Jack Walsh
Author-email: jwalshdev@gmail.com
License: UNKNOWN
Download-URL: https://github.com/jwalshdev/StockTrackr/archive/0.2.3.tar.gz
Platform: UNKNOWN
Classifier: Programming Language :: Python :: 3
Classifier: License :: OSI Approved :: MIT License
Classifier: Operating System :: OS Independent
